book/content/_build/html/_static/__init__.py
book/content/_build/jupyter_execute/installation.py
book/content/_build/jupyter_execute/starting.py
selector/__init__.py
selector/converter.py
selector/diversity.py
selector/similarity.py
selector/methods/__init__.py
selector/methods/base.py
selector/methods/distance.py
selector/methods/partition.py
selector/methods/similarity.py
selector/methods/utils.py
selector/methods/tests/__init__.py
selector/methods/tests/common.py
selector/methods/tests/test_distance.py
selector/methods/tests/test_partition.py
selector/tests/__init__.py
selector/tests/common.py
selector/tests/test_converter.py
selector/tests/test_diversity.py
selector/tests/test_similarity.py
selector/tests/data/ref_similarity_data.csv
selector_test-0.0.1.dist-info/LICENSE
selector_test-0.0.1.dist-info/METADATA
selector_test-0.0.1.dist-info/WHEEL
selector_test-0.0.1.dist-info/top_level.txt
selector_test-0.0.1.dist-info/zip-safe
selector_test-0.0.1.dist-info/RECORD
