Metadata-Version: 2.1
Name: selector-test
Version: 0.0.1
Summary: Molecule selection with maximum diversity.
Home-page: https://github.com/theochem/Selector
Author: QC-Devs Community
Author-email: QC-Devs Community <qcdevs@gmail.com>
License: GNU GENERAL PUBLIC LICENSE
Project-URL: homepage, https://github.com/theochem/Selector
Project-URL: documentation, https://selector.qcdevs.org/
Project-URL: repository, https://github.com/theochem/Selector
Keywords: subset selection,variable selection,chemical diversity,compound selection,maximum diversity,chemical library design,compound acquisition
Platform: Linux
Platform: Windows
Platform: MacOS
Classifier: Development Status :: 5 - Production/Stable
Classifier: Environment :: Console
Classifier: License :: OSI Approved :: GNU General Public License v3 (GPLv3)
Classifier: Natural Language :: English
Classifier: Operating System :: MacOS
Classifier: Operating System :: Microsoft :: Windows
Classifier: Operating System :: POSIX
Classifier: Operating System :: POSIX :: Linux
Classifier: Programming Language :: Python
Classifier: Programming Language :: Python :: 3
Classifier: Programming Language :: Python :: 3.9
Classifier: Programming Language :: Python :: 3.10
Classifier: Programming Language :: Python :: 3.11
Requires-Python: >=3.7
License-File: LICENSE
Requires-Dist: bitarray ~=2.5.1
Requires-Dist: importlib-resources >=5.6.0
Requires-Dist: numpy >=1.21.2
Requires-Dist: pandas >=1.3.5
Requires-Dist: pytest >=6.2.5
Requires-Dist: scikit-learn >=1.0.1
Requires-Dist: scipy ==1.11.1
Requires-Dist: setuptools >=58.0.4
Provides-Extra: dev
Requires-Dist: selector[exe,lint,test] ; extra == 'dev'
Provides-Extra: exe
Requires-Dist: setuptools ; extra == 'exe'
Requires-Dist: wheel ; extra == 'exe'
Requires-Dist: build ; extra == 'exe'
Requires-Dist: tomli ; extra == 'exe'
Requires-Dist: pyinstaller ; extra == 'exe'
Requires-Dist: staticx ; (platform_system == "Linux") and extra == 'exe'
Provides-Extra: lint
Requires-Dist: ruff ; extra == 'lint'
Requires-Dist: isort ; extra == 'lint'
Provides-Extra: test
Requires-Dist: pytest ==7.4.0 ; extra == 'test'
Requires-Dist: hypothesis ; extra == 'test'
Requires-Dist: pytest-cov >=3.0.0 ; extra == 'test'
Requires-Dist: tomli ; extra == 'test'
Requires-Dist: scikit-learn >=1.0.1 ; extra == 'test'
Requires-Dist: xdoctest ; extra == 'test'
Requires-Dist: Pygments ; extra == 'test'
